datazier/__init__.py
datazier-0.0.1.dist-info/licenses/LICENSE
datazier-0.0.1.dist-info/METADATA
datazier-0.0.1.dist-info/WHEEL
datazier-0.0.1.dist-info/top_level.txt
datazier-0.0.1.dist-info/RECORD
