Metadata-Version: 2.4
Name: datazier
Version: 0.0.1
Summary: Datazier - Coming soon
Author: Datazier
License: MIT
Project-URL: Homepage, https://github.com/datazier/datazier
Classifier: Development Status :: 1 - Planning
Classifier: Programming Language :: Python :: 3
Classifier: License :: OSI Approved :: MIT License
Classifier: Operating System :: OS Independent
Requires-Python: >=3.8
License-File: LICENSE
Dynamic: license-file
